[
    {
        "id": 0,
        "start": "0",
        "end": "10120",
        "speakers": "\"00\"",
        "text": "Se eu pegar essa ilha e esse helicóptero, e aí tudo faz sentido, porque aqui tem um zumbi e ali não tinha, e agora..."
    },
    {
        "id": 1,
        "start": "10120",
        "end": "15000",
        "speakers": "\"00\"",
        "text": "É isso! É isso! Eu sabia! Eu sabia! O Guaxaverso existe!"
    },
    {
        "id": 2,
        "start": "15120",
        "end": "15960",
        "speakers": "\"00\"",
        "text": "Como assim?"
    },
    {
        "id": 3,
        "start": "16180",
        "end": "18140",
        "speakers": "\"01, 00\"",
        "text": "Você entendeu a referência do último episódio?"
    },
    {
        "id": 4,
        "start": "18260",
        "end": "18980",
        "speakers": "\"00\"",
        "text": "Olha só, olha tudo!"
    },
    {
        "id": 5,
        "start": "18980",
        "end": "20020",
        "speakers": "\"01, 00\"",
        "text": "O Guaxaverso sabe o que faz!"
    },
    {
        "id": 6,
        "start": "20020",
        "end": "20960",
        "speakers": "\"01, 00\"",
        "text": "Espera! O que é o Guaxaverso?"
    },
    {
        "id": 7,
        "start": "21000",
        "end": "22980",
        "speakers": "\"01, 00\"",
        "text": "Era só uma questão de tempo!"
    },
    {
        "id": 8,
        "start": "23080",
        "end": "24700",
        "speakers": "\"00\"",
        "text": "Todos vão conhecer o Guaxaverso!"
    },
    {
        "id": 9,
        "start": "24700",
        "end": "27140",
        "speakers": "\"01, 00\"",
        "text": "Eu quero entender o Guaxaverso!"
    },
    {
        "id": 10,
        "start": "27220",
        "end": "28560",
        "speakers": "\"01, 00\"",
        "text": "Alguém me explica o que é o Guaxaverso?"
    },
    {
        "id": 11,
        "start": "28560",
        "end": "32020",
        "speakers": "\"00\"",
        "text": "É, pessoal, não existe o Guaxaverso."
    },
    {
        "id": 12,
        "start": "32080",
        "end": "33720",
        "speakers": "\"00\"",
        "text": "Eu acredito no Guaxaverso!"
    },
    {
        "id": 13,
        "start": "33760",
        "end": "36560",
        "speakers": "\"00\"",
        "text": "Mas supondo que ele exista..."
    },
    {
        "id": 14,
        "start": "37880",
        "end": "41520",
        "speakers": "\"00\"",
        "text": "Guaxaverso, onde o que não existe é debatido."
    },
    {
        "id": 15,
        "start": "44760",
        "end": "52540",
        "speakers": "\"00\"",
        "text": "Olá, eu sou o Marcelo Guaxinim, eu sou narrador, produtor, idealizador e podcaster do Realidades Paralelas do Guaxinim."
    },
    {
        "id": 16,
        "start": "52540",
        "end": "57220",
        "speakers": "\"00\"",
        "text": "Pra quem não sabe, o Guaxaverso é o nosso antigo escudo do mestre, que antes era no fim dos episódios,"
    },
    {
        "id": 17,
        "start": "57580",
        "end": "58540",
        "speakers": "\"00\"",
        "text": "e agora..."
    },
    {
        "id": 18,
        "start": "58560",
        "end": "62680",
        "speakers": "\"00\"",
        "text": "Ele se tornou um podcast próprio, que sai nas quintas-feiras, que não tem episódio regular."
    },
    {
        "id": 19,
        "start": "62900",
        "end": "67540",
        "speakers": "\"00\"",
        "text": "E nele, além de comentar sobre o episódio, eu leio seus comentários."
    },
    {
        "id": 20,
        "start": "68240",
        "end": "75140",
        "speakers": "\"00\"",
        "text": "Esse episódio vai falar sobre o episódio 66 do RPG Guaxa, Cavaleiros Arco-Íris, O Último Corvo."
    },
    {
        "id": 21,
        "start": "75440",
        "end": "80320",
        "speakers": "\"00\"",
        "text": "Acho que o mais básico que eu posso dizer pra vocês, ele é um Cavaleiros Arco-Íris Begins."
    },
    {
        "id": 22,
        "start": "80460",
        "end": "83860",
        "speakers": "\"00\"",
        "text": "Ele se passa antes de um outro episódio, que também tá no feed."
    },
    {
        "id": 23,
        "start": "84200",
        "end": "86560",
        "speakers": "\"00\"",
        "text": "Os Cavaleiros Arco-Íris foi o episódio 8 do RPG Guaxa."
    },
    {
        "id": 24,
        "start": "86560",
        "end": "88560",
        "speakers": "\"00\"",
        "text": "É um episódio muito amado por todo mundo."
    },
    {
        "id": 25,
        "start": "88560",
        "end": "93120",
        "speakers": "\"00\"",
        "text": "Muitos falaram no post dele, tem arte dos fãs, o pessoal comentou bastante na época."
    },
    {
        "id": 26,
        "start": "93480",
        "end": "103400",
        "speakers": "\"00\"",
        "text": "Esse episódio foi gravado no início de janeiro de 2020, mas aí ele foi pra um editor que, durante a pandemia, acabou não tendo mais tempo pra editar."
    },
    {
        "id": 27,
        "start": "103980",
        "end": "111120",
        "speakers": "\"00\"",
        "text": "Aí ficou bastante tempo com ele, depois ele me repassou de volta o episódio, e daí eu passei pro Rafael Zorzal, que foi quem acabou editando, né?"
    },
    {
        "id": 28,
        "start": "111400",
        "end": "114140",
        "speakers": "\"00\"",
        "text": "O Rafael Zorzal já tinha outros episódios pra editar, ele foi deixando."
    },
    {
        "id": 29,
        "start": "114140",
        "end": "116800",
        "speakers": "\"00\"",
        "text": "Então esse episódio acabou ficando um ano parado."
    },
    {
        "id": 30,
        "start": "117340",
        "end": "118440",
        "speakers": "\"00\"",
        "text": "Os jogadores até achavam que..."
    },
    {
        "id": 31,
        "start": "118560",
        "end": "121320",
        "speakers": "\"00\"",
        "text": "Não sei mais, mas a culpa não foi minha, né?"
    },
    {
        "id": 32,
        "start": "121400",
        "end": "124560",
        "speakers": "\"00\"",
        "text": "Foi, sei lá, rolou uma pandemia que acabou afetando algumas pessoas."
    },
    {
        "id": 33,
        "start": "125000",
        "end": "129840",
        "speakers": "\"00\"",
        "text": "Mas respondendo as perguntas que vocês deixaram no post, o primeiro comentário lá é do Todê Zistino."
    },
    {
        "id": 34,
        "start": "130300",
        "end": "131160",
        "speakers": "\"00\"",
        "text": "Ele escreveu..."
    },
    {
        "id": 35,
        "start": "131160",
        "end": "137160",
        "speakers": "\"00\"",
        "text": "Ótimo cast."
    },
    {
        "id": 36,
        "start": "137520",
        "end": "139580",
        "speakers": "\"00\"",
        "text": "Aí ele botou escondidinho, né?"
    },
    {
        "id": 37,
        "start": "139580",
        "end": "145560",
        "speakers": "\"00\"",
        "text": "A Dona Corva, trazida pelas arpias, que curte gatos, é a velha do episódio 1 das gatas?"
    },
    {
        "id": 38,
        "start": "146000",
        "end": "147720",
        "speakers": "\"00\"",
        "text": "Teoria do Big N, brincando."
    },
    {
        "id": 39,
        "start": "148020",
        "end": "148480",
        "speakers": "\"00\"",
        "text": "Não, não é."
    },
    {
        "id": 40,
        "start": "148480",
        "end": "150120",
        "speakers": "\"00\"",
        "text": "Não é ela, mas..."
    },
    {
        "id": 41,
        "start": "150120",
        "end": "153300",
        "speakers": "\"00\"",
        "text": "Bruxas costumam gostar de gatos, fica o registro."
    },
    {
        "id": 42,
        "start": "153580",
        "end": "156000",
        "speakers": "\"00\"",
        "text": "Bruno Camargo de Oliveira, como sempre, ótimo episódio."
    },
    {
        "id": 43,
        "start": "156120",
        "end": "156680",
        "speakers": "\"00\"",
        "text": "Obrigado, Bruno."
    },
    {
        "id": 44,
        "start": "157100",
        "end": "157540",
        "speakers": "\"00\"",
        "text": "Spoiler."
    },
    {
        "id": 45,
        "start": "157900",
        "end": "161080",
        "speakers": "\"00\"",
        "text": "Chorei rindo do anil ser fissurado em rabão desde criança."
    },
    {
        "id": 46,
        "start": "161620",
        "end": "165220",
        "speakers": "\"00\"",
        "text": "A família Corvo são os antecessores do Corvo do segundo episódio?"
    },
    {
        "id": 47,
        "start": "165620",
        "end": "167380",
        "speakers": "\"00\"",
        "text": "Ou são criadores de cela terrorista?"
    },
    {
        "id": 48,
        "start": "167680",
        "end": "169700",
        "speakers": "\"00\"",
        "text": "Não, pessoal, eu apenas gosto de Corvo, gente."
    },
    {
        "id": 49,
        "start": "169740",
        "end": "170220",
        "speakers": "\"00\"",
        "text": "É só isso."
    },
    {
        "id": 50,
        "start": "170380",
        "end": "170720",
        "speakers": "\"00\"",
        "text": "Calma."
    },
    {
        "id": 51,
        "start": "171120",
        "end": "177080",
        "speakers": "\"00\"",
        "text": "Esse episódio, esse sim, 100% de certeza, não tem ligação com o episódio do Corvo, tá?"
    },
    {
        "id": 52,
        "start": "177080",
        "end": "178320",
        "speakers": "\"00\"",
        "text": "E sim, esse..."
    },
    {
        "id": 53,
        "start": "178320",
        "end": "181120",
        "speakers": "\"00\"",
        "text": "Mais um Cavaleiros do Arco-Íris Begins é um anil Begins."
    },
    {
        "id": 54,
        "start": "181400",
        "end": "183360",
        "speakers": "\"00\"",
        "text": "Onyx Def escreveu."
    },
    {
        "id": 55,
        "start": "183440",
        "end": "184640",
        "speakers": "\"00\"",
        "text": "Terminei o episódio pensando."
    },
    {
        "id": 56,
        "start": "185160",
        "end": "190080",
        "speakers": "\"00\"",
        "text": "Em uma batalha crossover entre Cavaleiros do Arco-Íris e Cavaleiros do Bicho, quem ganha?"
    },
    {
        "id": 57,
        "start": "190420",
        "end": "195660",
        "speakers": "\"00\"",
        "text": "Então, os Cavaleiros do Arco-Íris são soldados bem treinados com uma espada e uma capa colorida."
    },
    {
        "id": 58,
        "start": "195920",
        "end": "199360",
        "speakers": "\"00\"",
        "text": "Os Cavaleiros do Bicho, eles são personagens de anime."
    },
    {
        "id": 59,
        "start": "199760",
        "end": "201580",
        "speakers": "\"00\"",
        "text": "Então eles acabam sendo um pouquinho mais poderosos."
    },
    {
        "id": 60,
        "start": "201940",
        "end": "206440",
        "speakers": "\"00\"",
        "text": "Eu esperaria o episódio 4 de Cavaleiros do Arco-Íris, que tá atrasado também, a gente peça desculpa."
    },
    {
        "id": 61,
        "start": "206440",
        "end": "207440",
        "speakers": "\"00\"",
        "text": "Mas também..."
    },
    {
        "id": 62,
        "start": "208320",
        "end": "212160",
        "speakers": "\"00\"",
        "text": "Volto a dizer, pra quem não notou, ano passado foi um ano diferente."
    },
    {
        "id": 63,
        "start": "212440",
        "end": "214220",
        "speakers": "\"00\"",
        "text": "Mas eu apostaria nos Cavaleiros do Bicho."
    },
    {
        "id": 64,
        "start": "214540",
        "end": "217620",
        "speakers": "\"00\"",
        "text": "Espero que eles nunca precisem se enfrentar, pra ser mais exato, né?"
    },
    {
        "id": 65,
        "start": "217900",
        "end": "218800",
        "speakers": "\"00\"",
        "text": "Ivan Rabelo!"
    },
    {
        "id": 66,
        "start": "219040",
        "end": "221720",
        "speakers": "\"00\"",
        "text": "Opa, primeira vez que eu tomo coragem de comentar aqui."
    },
    {
        "id": 67,
        "start": "222160",
        "end": "223100",
        "speakers": "\"00\"",
        "text": "Não precisa ter coragem, gente."
    },
    {
        "id": 68,
        "start": "223160",
        "end": "224160",
        "speakers": "\"00\"",
        "text": "É só escrever qualquer coisa."
    },
    {
        "id": 69,
        "start": "224280",
        "end": "226660",
        "speakers": "\"00\"",
        "text": "Eu gravo qualquer coisa e lanço no feed, se vocês gostam."
    },
    {
        "id": 70,
        "start": "226820",
        "end": "227920",
        "speakers": "\"00\"",
        "text": "Você pode escrever qualquer coisa também."
    },
    {
        "id": 71,
        "start": "228520",
        "end": "230520",
        "speakers": "\"00\"",
        "text": "Eu estou com uma dúvida sobre a magia desse mundo."
    },
    {
        "id": 72,
        "start": "230620",
        "end": "232840",
        "speakers": "\"00\"",
        "text": "Sabemos que a família gato se transforma em gato na floresta."
    },
    {
        "id": 73,
        "start": "233020",
        "end": "234780",
        "speakers": "\"00\"",
        "text": "A família corvo em corvos."
    },
    {
        "id": 74,
        "start": "234880",
        "end": "235640",
        "speakers": "\"00\"",
        "text": "E assim por diante."
    },
    {
        "id": 75,
        "start": "236120",
        "end": "237280",
        "speakers": "\"00\"",
        "text": "Spoiler do início do episódio."
    },
    {
        "id": 76,
        "start": "237660",
        "end": "238300",
        "speakers": "\"00\"",
        "text": "Mas o que acontece?"
    },
    {
        "id": 77,
        "start": "238320",
        "end": "240060",
        "speakers": "\"00\"",
        "text": "O que acontece quando uma família se mistura?"
    },
    {
        "id": 78,
        "start": "240340",
        "end": "242880",
        "speakers": "\"00\"",
        "text": "Se o casamento tivesse acontecido no início do episódio,"
    },
    {
        "id": 79,
        "start": "243040",
        "end": "246580",
        "speakers": "\"00\"",
        "text": "o que prevaleceria na hora da floresta fazer sua magia?"
    },
    {
        "id": 80,
        "start": "246780",
        "end": "248080",
        "speakers": "\"00\"",
        "text": "Corvo ou aranha?"
    },
    {
        "id": 81,
        "start": "248560",
        "end": "250280",
        "speakers": "\"00\"",
        "text": "Essa magia só se aplica a esse povo?"
    },
    {
        "id": 82,
        "start": "250500",
        "end": "251820",
        "speakers": "\"00\"",
        "text": "Ou é uma coisa da floresta?"
    },
    {
        "id": 83,
        "start": "252160",
        "end": "255580",
        "speakers": "\"00\"",
        "text": "E quem quer que entre, pode e vai ser afetado por ela?"
    },
    {
        "id": 84,
        "start": "255960",
        "end": "260760",
        "speakers": "\"00\"",
        "text": "Isso tem alguma ligação com a dimensão da Sinem no episódio da Xerife?"
    },
    {
        "id": 85,
        "start": "261100",
        "end": "263380",
        "speakers": "\"00\"",
        "text": "E são as centelhas mágicas alterando as pessoas"
    },
    {
        "id": 86,
        "start": "263380",
        "end": "266340",
        "speakers": "\"00\"",
        "text": "e transformando esse povo em híbridos animais"
    },
    {
        "id": 87,
        "start": "266340",
        "end": "268300",
        "speakers": "\"00\"",
        "text": "ou outros povos em elfos?"
    },
    {
        "id": 88,
        "start": "268320",
        "end": "270240",
        "speakers": "\"00\"",
        "text": "Vamos por partes."
    },
    {
        "id": 89,
        "start": "270300",
        "end": "270760",
        "speakers": "\"00\"",
        "text": "Vamos lá."
    },
    {
        "id": 90,
        "start": "271100",
        "end": "273400",
        "speakers": "\"00\"",
        "text": "Nesse mundo, quando duas famílias casam,"
    },
    {
        "id": 91,
        "start": "273760",
        "end": "276220",
        "speakers": "\"00\"",
        "text": "o casal escolhe um sobrenome para si."
    },
    {
        "id": 92,
        "start": "276640",
        "end": "278580",
        "speakers": "\"00\"",
        "text": "Normalmente, não envolve ser homem ou mulher,"
    },
    {
        "id": 93,
        "start": "279040",
        "end": "282380",
        "speakers": "\"00\"",
        "text": "mas da família mais importante,"
    },
    {
        "id": 94,
        "start": "282780",
        "end": "284200",
        "speakers": "\"00\"",
        "text": "costuma prevalecer."
    },
    {
        "id": 95,
        "start": "284520",
        "end": "286320",
        "speakers": "\"00\"",
        "text": "Tu escolheu teu sobrenome, ele é teu sobrenome."
    },
    {
        "id": 96,
        "start": "287160",
        "end": "289920",
        "speakers": "\"00\"",
        "text": "O teu sobrenome da família, caso tu tenha mudado,"
    },
    {
        "id": 97,
        "start": "290280",
        "end": "291540",
        "speakers": "\"00\"",
        "text": "ele se torna secundário."
    },
    {
        "id": 98,
        "start": "291840",
        "end": "293460",
        "speakers": "\"00\"",
        "text": "Da mesma forma que os Cavaleiros dos Arco-Íris"
    },
    {
        "id": 99,
        "start": "293460",
        "end": "294700",
        "speakers": "\"00\"",
        "text": "se tornaram cavaleiros,"
    },
    {
        "id": 100,
        "start": "295140",
        "end": "297940",
        "speakers": "\"00\"",
        "text": "o seu sobrenome é apagado, né?"
    },
    {
        "id": 101,
        "start": "297940",
        "end": "300160",
        "speakers": "\"00\"",
        "text": "Embora, no fundo, como a gente viu,"
    },
    {
        "id": 102,
        "start": "300520",
        "end": "301880",
        "speakers": "\"00\"",
        "text": "o Cavaleiro Anil original,"
    },
    {
        "id": 103,
        "start": "302240",
        "end": "303880",
        "speakers": "\"00\"",
        "text": "ele ainda se sentia um corvo."
    },
    {
        "id": 104,
        "start": "304220",
        "end": "305720",
        "speakers": "\"00\"",
        "text": "Mas se, por exemplo, ele fosse para a floresta,"
    },
    {
        "id": 105,
        "start": "306120",
        "end": "307540",
        "speakers": "\"00\"",
        "text": "ele permaneceria puro."
    },
    {
        "id": 106,
        "start": "307900",
        "end": "310740",
        "speakers": "\"00\"",
        "text": "Essa é uma das ideias de quando os Cavaleiros dos Arco-Íris"
    },
    {
        "id": 107,
        "start": "310740",
        "end": "312060",
        "speakers": "\"00\"",
        "text": "foram criados lá atrás."
    },
    {
        "id": 108,
        "start": "312420",
        "end": "314780",
        "speakers": "\"00\"",
        "text": "Essa magia da transformação é da floresta."
    },
    {
        "id": 109,
        "start": "315120",
        "end": "316200",
        "speakers": "\"00\"",
        "text": "A muralha em volta da cidade,"
    },
    {
        "id": 110,
        "start": "316280",
        "end": "317680",
        "speakers": "\"00\"",
        "text": "como a gente viu lá no episódio 8,"
    },
    {
        "id": 111,
        "start": "318000",
        "end": "321300",
        "speakers": "\"00\"",
        "text": "ela serve para evitar que essa magia entre na cidade."
    },
    {
        "id": 112,
        "start": "321720",
        "end": "322980",
        "speakers": "\"00\"",
        "text": "Tem alguma coisa a ver com a Sinem?"
    },
    {
        "id": 113,
        "start": "323120",
        "end": "323480",
        "speakers": "\"00\"",
        "text": "Não."
    },
    {
        "id": 114,
        "start": "323680",
        "end": "325700",
        "speakers": "\"00\"",
        "text": "Os elfos vão ser explicados em outro episódio"
    },
    {
        "id": 115,
        "start": "325700",
        "end": "326920",
        "speakers": "\"00\"",
        "text": "que sai esse semestre ainda,"
    },
    {
        "id": 116,
        "start": "327320",
        "end": "327760",
        "speakers": "\"00\"",
        "text": "mas os elfos vão ser explicados em outro episódio."
    },
    {
        "id": 117,
        "start": "327760",
        "end": "327920",
        "speakers": "\"00\"",
        "text": "Mas os elfos vão ser explicados em outro episódio."
    },
    {
        "id": 118,
        "start": "327920",
        "end": "330260",
        "speakers": "\"00\"",
        "text": "Os elfos, por exemplo, os provos mágicos,"
    },
    {
        "id": 119,
        "start": "330560",
        "end": "332320",
        "speakers": "\"00\"",
        "text": "ele vem de uma outra criação."
    },
    {
        "id": 120,
        "start": "332640",
        "end": "334140",
        "speakers": "\"00\"",
        "text": "Então aguarde que vem coisa por aí."
    },
    {
        "id": 121,
        "start": "334380",
        "end": "335680",
        "speakers": "\"00\"",
        "text": "Ana Curata escreveu."
    },
    {
        "id": 122,
        "start": "335740",
        "end": "337360",
        "speakers": "\"00\"",
        "text": "Adorei o episódio. Muito leve e gostoso."
    },
    {
        "id": 123,
        "start": "337500",
        "end": "339180",
        "speakers": "\"00\"",
        "text": "Sem teorias, apenas meu agradecimento."
    },
    {
        "id": 124,
        "start": "339420",
        "end": "341900",
        "speakers": "\"00\"",
        "text": "Muito obrigado, Ana. A ideia realmente era ter um episódio mais leve"
    },
    {
        "id": 125,
        "start": "341900",
        "end": "344220",
        "speakers": "\"00\"",
        "text": "agora em janeiro. Muito obrigado pelo seu comentário."
    },
    {
        "id": 126,
        "start": "344520",
        "end": "346120",
        "speakers": "\"00\"",
        "text": "Muito obrigado por estar sempre aí nos ouvindo."
    },
    {
        "id": 127,
        "start": "346440",
        "end": "348320",
        "speakers": "\"00\"",
        "text": "O Leonardo Doni escreveu."
    },
    {
        "id": 128,
        "start": "348320",
        "end": "349140",
        "speakers": "\"00\"",
        "text": "Episódio incrível."
    },
    {
        "id": 129,
        "start": "349640",
        "end": "351380",
        "speakers": "\"00\"",
        "text": "Nem vi o tempo passar enquanto ouvia."
    },
    {
        "id": 130,
        "start": "351700",
        "end": "353920",
        "speakers": "\"00\"",
        "text": "Só fiquei com uma dúvida. Os jogadores teriam como descobrir"
    },
    {
        "id": 131,
        "start": "353920",
        "end": "355040",
        "speakers": "\"00\"",
        "text": "a linhagem do Anil?"
    },
    {
        "id": 132,
        "start": "355040",
        "end": "357740",
        "speakers": "\"00\"",
        "text": "Se sim, como você lidaria com a desconfiança"
    },
    {
        "id": 133,
        "start": "357740",
        "end": "359960",
        "speakers": "\"00\"",
        "text": "que essa informação traria a eles?"
    },
    {
        "id": 134,
        "start": "360180",
        "end": "361400",
        "speakers": "\"00\"",
        "text": "Essa é a magia do RPG."
    },
    {
        "id": 135,
        "start": "361840",
        "end": "363900",
        "speakers": "\"00\"",
        "text": "De cabeça, eu não sei como eles poderiam descobrir"
    },
    {
        "id": 136,
        "start": "363900",
        "end": "365780",
        "speakers": "\"00\"",
        "text": "da linhagem do Anil, mas eles poderiam"
    },
    {
        "id": 137,
        "start": "365780",
        "end": "367500",
        "speakers": "\"00\"",
        "text": "tentar pesquisar alguma coisa, talvez."
    },
    {
        "id": 138,
        "start": "367700",
        "end": "369880",
        "speakers": "\"00\"",
        "text": "É bem complicado. E se acontecesse,"
    },
    {
        "id": 139,
        "start": "369940",
        "end": "371480",
        "speakers": "\"00\"",
        "text": "eu como mestre teria que dar um jeito"
    },
    {
        "id": 140,
        "start": "371480",
        "end": "373280",
        "speakers": "\"00\"",
        "text": "de contornar a situação, né?"
    },
    {
        "id": 141,
        "start": "373520",
        "end": "375940",
        "speakers": "\"00\"",
        "text": "Como foi o caso do casamento, que eu vou comentar mais abaixo"
    },
    {
        "id": 142,
        "start": "375940",
        "end": "377560",
        "speakers": "\"00\"",
        "text": "que eu sei que alguém perguntou."
    },
    {
        "id": 143,
        "start": "377940",
        "end": "380300",
        "speakers": "\"00\"",
        "text": "Mas a princípio, eu teria que me virar."
    },
    {
        "id": 144,
        "start": "380540",
        "end": "381740",
        "speakers": "\"00\"",
        "text": "Rafael Pigoso escreveu."
    },
    {
        "id": 145,
        "start": "382400",
        "end": "383980",
        "speakers": "\"00\"",
        "text": "Olá! Primeira vez que comento"
    },
    {
        "id": 146,
        "start": "383980",
        "end": "385380",
        "speakers": "\"00\"",
        "text": "porque finalmente consegui ouvir"
    },
    {
        "id": 147,
        "start": "385380",
        "end": "387360",
        "speakers": "\"00\"",
        "text": "com antecedência o episódio."
    },
    {
        "id": 148,
        "start": "387740",
        "end": "389600",
        "speakers": "\"00\"",
        "text": "Adorei o começo do episódio com a discussão"
    },
    {
        "id": 149,
        "start": "389600",
        "end": "391880",
        "speakers": "\"00\"",
        "text": "política. Gostei das várias referências"
    },
    {
        "id": 150,
        "start": "391880",
        "end": "393580",
        "speakers": "\"00\"",
        "text": "às situações do nosso mundo em relação"
    },
    {
        "id": 151,
        "start": "393580",
        "end": "395580",
        "speakers": "\"00\"",
        "text": "a eleições. Foi intencional"
    },
    {
        "id": 152,
        "start": "395580",
        "end": "397800",
        "speakers": "\"00\"",
        "text": "ou foi subconsciente? Em especial"
    },
    {
        "id": 153,
        "start": "397800",
        "end": "399900",
        "speakers": "\"00\"",
        "text": "o comentário do Ricardo, sobre não ser"
    },
    {
        "id": 154,
        "start": "399900",
        "end": "401800",
        "speakers": "\"00\"",
        "text": "a hora de aventuras. Isso lembrou"
    },
    {
        "id": 155,
        "start": "401800",
        "end": "403640",
        "speakers": "\"00\"",
        "text": "tanto o editorial de um certo jornal"
    },
    {
        "id": 156,
        "start": "403640",
        "end": "405360",
        "speakers": "\"00\"",
        "text": "para as eleições paulistanas."
    },
    {
        "id": 157,
        "start": "405700",
        "end": "407760",
        "speakers": "\"00\"",
        "text": "Eu gravei isso em janeiro. Os jogadores estão de prova."
    },
    {
        "id": 158,
        "start": "408160",
        "end": "409800",
        "speakers": "\"00\"",
        "text": "É óbvio que o RPG Guaxa,"
    },
    {
        "id": 159,
        "start": "409940",
        "end": "412060",
        "speakers": "\"00\"",
        "text": "como qualquer produção no universo,"
    },
    {
        "id": 160,
        "start": "412500",
        "end": "413980",
        "speakers": "\"00\"",
        "text": "ela acaba tendo"
    },
    {
        "id": 161,
        "start": "413980",
        "end": "415560",
        "speakers": "\"00\"",
        "text": "uma influênciazinha política."
    },
    {
        "id": 162,
        "start": "415960",
        "end": "417720",
        "speakers": "\"00\"",
        "text": "Isso é inevitável, gente. Tudo é política."
    },
    {
        "id": 163,
        "start": "417740",
        "end": "419420",
        "speakers": "\"00\"",
        "text": "Tudo é político no mundo. Mas"
    },
    {
        "id": 164,
        "start": "419420",
        "end": "421920",
        "speakers": "\"00\"",
        "text": "não foi nada assim direcionado"
    },
    {
        "id": 165,
        "start": "421920",
        "end": "423580",
        "speakers": "\"00\"",
        "text": "e intencional. Foi apenas"
    },
    {
        "id": 166,
        "start": "423580",
        "end": "425640",
        "speakers": "\"00\"",
        "text": "uma ideia geral a ser debatida ali."
    },
    {
        "id": 167,
        "start": "425880",
        "end": "427440",
        "speakers": "\"00\"",
        "text": "Já outra pergunta que fiquei"
    },
    {
        "id": 168,
        "start": "427440",
        "end": "429420",
        "speakers": "\"00\"",
        "text": "foi sobre o poder da Ariadne."
    },
    {
        "id": 169,
        "start": "429700",
        "end": "431760",
        "speakers": "\"00\"",
        "text": "A personagem tentou usar algo relacionado"
    },
    {
        "id": 170,
        "start": "431760",
        "end": "433660",
        "speakers": "\"00\"",
        "text": "ao seu sobrenome. Porém, não era bem"
    },
    {
        "id": 171,
        "start": "433660",
        "end": "435620",
        "speakers": "\"00\"",
        "text": "o que foi proposto. Pode falar qual"
    },
    {
        "id": 172,
        "start": "435620",
        "end": "437580",
        "speakers": "\"00\"",
        "text": "seria o poder dela e dos corvos?"
    },
    {
        "id": 173,
        "start": "438100",
        "end": "439640",
        "speakers": "\"00\"",
        "text": "Novamente, parabéns pelo episódio"
    },
    {
        "id": 174,
        "start": "439640",
        "end": "441300",
        "speakers": "\"00\"",
        "text": "ao mestre e aos jogadores."
    },
    {
        "id": 175,
        "start": "441760",
        "end": "443760",
        "speakers": "\"00\"",
        "text": "O poder, tu diz, do animal"
    },
    {
        "id": 176,
        "start": "443760",
        "end": "445800",
        "speakers": "\"00\"",
        "text": "é porque uma coisa é o teu"
    },
    {
        "id": 177,
        "start": "445800",
        "end": "447720",
        "speakers": "\"00\"",
        "text": "olho enxergar um pouco melhor como o da coruja."
    },
    {
        "id": 178,
        "start": "447740",
        "end": "449780",
        "speakers": "\"00\"",
        "text": "A outra é tu começar a produzir"
    },
    {
        "id": 179,
        "start": "449780",
        "end": "451860",
        "speakers": "\"00\"",
        "text": "teia, sei lá, alguma coisa que poderia acontecer."
    },
    {
        "id": 180,
        "start": "452140",
        "end": "453680",
        "speakers": "\"00\"",
        "text": "Talvez levasse muito mais tempo."
    },
    {
        "id": 181,
        "start": "454000",
        "end": "455680",
        "speakers": "\"00\"",
        "text": "Talvez ela tivesse uma facilidade pra"
    },
    {
        "id": 182,
        "start": "455680",
        "end": "457840",
        "speakers": "\"00\"",
        "text": "escalar, tipo Homem-Aranha. Mas, assim,"
    },
    {
        "id": 183,
        "start": "458400",
        "end": "459720",
        "speakers": "\"00\"",
        "text": "ia dependendo do que o jogador"
    },
    {
        "id": 184,
        "start": "459720",
        "end": "461840",
        "speakers": "\"00\"",
        "text": "me falasse e da situação a gente ia"
    },
    {
        "id": 185,
        "start": "461840",
        "end": "463660",
        "speakers": "\"00\"",
        "text": "criando ali em cima. Uma história"
    },
    {
        "id": 186,
        "start": "463660",
        "end": "465900",
        "speakers": "\"00\"",
        "text": "coletiva, né? Mas, a princípio,"
    },
    {
        "id": 187,
        "start": "465920",
        "end": "467640",
        "speakers": "\"00\"",
        "text": "eu não tinha pensado nada. Até porque"
    },
    {
        "id": 188,
        "start": "467640",
        "end": "469800",
        "speakers": "\"00\"",
        "text": "quando eu pensei na aventura, eu não"
    },
    {
        "id": 189,
        "start": "469800",
        "end": "471680",
        "speakers": "\"00\"",
        "text": "sabia com antecedência qual era o"
    },
    {
        "id": 190,
        "start": "471680",
        "end": "473740",
        "speakers": "\"00\"",
        "text": "sobrenome dos jogadores. Eu disse"
    },
    {
        "id": 191,
        "start": "473740",
        "end": "475720",
        "speakers": "\"00\"",
        "text": "pros jogadores, vocês podem ter o animal que quiser de sobrenome,"
    },
    {
        "id": 192,
        "start": "475720",
        "end": "477720",
        "speakers": "\"00\"",
        "text": "menos corvo, porque corvo"
    },
    {
        "id": 193,
        "start": "477740",
        "end": "479560",
        "speakers": "\"00\"",
        "text": "vai ser de um NPC que já tá pronto."
    },
    {
        "id": 194,
        "start": "479860",
        "end": "481680",
        "speakers": "\"00\"",
        "text": "E daí eles, cada um pensou o que"
    },
    {
        "id": 195,
        "start": "481680",
        "end": "483660",
        "speakers": "\"00\"",
        "text": "queria, né? Não sei. Dependendo do que o jogador"
    },
    {
        "id": 196,
        "start": "483660",
        "end": "485420",
        "speakers": "\"00\"",
        "text": "falasse, a gente podia tentar criar alguma coisa."
    },
    {
        "id": 197,
        "start": "485720",
        "end": "487660",
        "speakers": "\"00\"",
        "text": "Mas teria que ser algo sutil, porque a transformação"
    },
    {
        "id": 198,
        "start": "487660",
        "end": "490000",
        "speakers": "\"00\"",
        "text": "leva muito tempo. A própria Matilda,"
    },
    {
        "id": 199,
        "start": "490060",
        "end": "491340",
        "speakers": "\"00\"",
        "text": "que tá há anos na floresta,"
    },
    {
        "id": 200,
        "start": "491680",
        "end": "493680",
        "speakers": "\"00\"",
        "text": "ela ainda não virou uma arpia, que é o"
    },
    {
        "id": 201,
        "start": "493680",
        "end": "495600",
        "speakers": "\"00\"",
        "text": "destino que ela vai tomar. Ela tava querendo"
    },
    {
        "id": 202,
        "start": "495600",
        "end": "497580",
        "speakers": "\"00\"",
        "text": "penas e tal, mas ela ainda não conseguia voar."
    },
    {
        "id": 203,
        "start": "497880",
        "end": "499980",
        "speakers": "\"00\"",
        "text": "E um dia, talvez, todos ali sejam corvos."
    },
    {
        "id": 204,
        "start": "500380",
        "end": "501640",
        "speakers": "\"00\"",
        "text": "O Alan Betelli"
    },
    {
        "id": 205,
        "start": "501640",
        "end": "503600",
        "speakers": "\"00\"",
        "text": "escreveu, eu queria ver um episódio"
    },
    {
        "id": 206,
        "start": "503600",
        "end": "505620",
        "speakers": "\"00\"",
        "text": "e se o candidato da família corvo"
    },
    {
        "id": 207,
        "start": "505620",
        "end": "507580",
        "speakers": "\"00\"",
        "text": "aceitasse o casamento. Aliás, fica"
    },
    {
        "id": 208,
        "start": "507580",
        "end": "509740",
        "speakers": "\"00\"",
        "text": "a dica, Guaxa. Uma meta pra fazer"
    },
    {
        "id": 209,
        "start": "509740",
        "end": "511480",
        "speakers": "\"00\"",
        "text": "episódios curtinhos, contando alguns"
    },
    {
        "id": 210,
        "start": "511480",
        "end": "513740",
        "speakers": "\"00\"",
        "text": "e se de episódios emblemáticos."
    },
    {
        "id": 211,
        "start": "514620",
        "end": "515780",
        "speakers": "\"00\"",
        "text": "Olha, é uma ideia bacana,"
    },
    {
        "id": 212,
        "start": "515900",
        "end": "517880",
        "speakers": "\"00\"",
        "text": "eu posso pensar nisso. Seria mais trabalho pra mim,"
    },
    {
        "id": 213,
        "start": "517980",
        "end": "519460",
        "speakers": "\"00\"",
        "text": "que por enquanto não tá dando, eu mal tô"
    },
    {
        "id": 214,
        "start": "519460",
        "end": "521480",
        "speakers": "\"00\"",
        "text": "tendo tempo de fazer as outras coisas. Mas, ok, tá"
    },
    {
        "id": 215,
        "start": "521480",
        "end": "523280",
        "speakers": "\"00\"",
        "text": "anotado aqui. É uma excelente ideia."
    },
    {
        "id": 216,
        "start": "523780",
        "end": "525520",
        "speakers": "\"00\"",
        "text": "O gargalo é tempo, né? A gente"
    },
    {
        "id": 217,
        "start": "525520",
        "end": "527420",
        "speakers": "\"00\"",
        "text": "pra tá dedicando a isso. Mas sim,"
    },
    {
        "id": 218,
        "start": "527520",
        "end": "529440",
        "speakers": "\"00\"",
        "text": "é uma ideia. É engraçado que"
    },
    {
        "id": 219,
        "start": "529440",
        "end": "531920",
        "speakers": "\"00\"",
        "text": "quando a jogadora Sabrina propôs o casamento,"
    },
    {
        "id": 220,
        "start": "532360",
        "end": "533880",
        "speakers": "\"00\"",
        "text": "eu fiquei totalmente sem reação,"
    },
    {
        "id": 221,
        "start": "534040",
        "end": "535560",
        "speakers": "\"00\"",
        "text": "porque isso tiraria todo"
    },
    {
        "id": 222,
        "start": "535560",
        "end": "537060",
        "speakers": "\"00\"",
        "text": "o foco da aventura, né?"
    },
    {
        "id": 223,
        "start": "537580",
        "end": "539620",
        "speakers": "\"00\"",
        "text": "Se o Ricardo Corvo aceitasse,"
    },
    {
        "id": 224,
        "start": "539960",
        "end": "541880",
        "speakers": "\"00\"",
        "text": "a aventura não teria porquê continuar."
    },
    {
        "id": 225,
        "start": "542260",
        "end": "543660",
        "speakers": "\"00\"",
        "text": "Então eu dei ali o migué dele"
    },
    {
        "id": 226,
        "start": "543660",
        "end": "545600",
        "speakers": "\"00\"",
        "text": "fugir. Mas..."
    },
    {
        "id": 227,
        "start": "545600",
        "end": "547540",
        "speakers": "\"00\"",
        "text": "É uma ideia, talvez. E se tivessem"
    },
    {
        "id": 228,
        "start": "547540",
        "end": "549680",
        "speakers": "\"00\"",
        "text": "se casado, né? Talvez o Anil"
    },
    {
        "id": 229,
        "start": "549680",
        "end": "551380",
        "speakers": "\"00\"",
        "text": "continuaria escondido,"
    },
    {
        "id": 230,
        "start": "551740",
        "end": "553760",
        "speakers": "\"00\"",
        "text": "tentando armar um golpe pra tirar"
    },
    {
        "id": 231,
        "start": "553760",
        "end": "555560",
        "speakers": "\"00\"",
        "text": "do poder a Ariadne?"
    },
    {
        "id": 232,
        "start": "555900",
        "end": "557580",
        "speakers": "\"00\"",
        "text": "Não sei. Último comentário é do"
    },
    {
        "id": 233,
        "start": "557580",
        "end": "559840",
        "speakers": "\"00\"",
        "text": "Ananta. Sem muitas perguntas"
    },
    {
        "id": 234,
        "start": "559840",
        "end": "561320",
        "speakers": "\"00\"",
        "text": "nesse, mas vim parabenizar,"
    },
    {
        "id": 235,
        "start": "561680",
        "end": "563520",
        "speakers": "\"00\"",
        "text": "porque a dimensão do arco-íris é minha"
    },
    {
        "id": 236,
        "start": "563520",
        "end": "565500",
        "speakers": "\"00\"",
        "text": "favorita. Que bom, foi um prazer"
    },
    {
        "id": 237,
        "start": "565500",
        "end": "567320",
        "speakers": "\"00\"",
        "text": "revisitar. Eu pretendo revisitar ela mais vezes."
    },
    {
        "id": 238,
        "start": "567580",
        "end": "569660",
        "speakers": "\"00\"",
        "text": "Mesmo sem super mistérios, pelo menos na primeira"
    },
    {
        "id": 239,
        "start": "569660",
        "end": "571680",
        "speakers": "\"00\"",
        "text": "vez, né? Agora que eu sei que tá tudo"
    },
    {
        "id": 240,
        "start": "571680",
        "end": "573740",
        "speakers": "\"00\"",
        "text": "conectado, dá pra ficar imaginando qual é a realidade"
    },
    {
        "id": 241,
        "start": "573740",
        "end": "575540",
        "speakers": "\"00\"",
        "text": "que ela se encaixa, em um lugar tão"
    },
    {
        "id": 242,
        "start": "575540",
        "end": "577620",
        "speakers": "\"00\"",
        "text": "aconchegante. Acho que essa é a palavra."
    },
    {
        "id": 243,
        "start": "577860",
        "end": "579240",
        "speakers": "\"00\"",
        "text": "Apesar dos nojentinhos"
    },
    {
        "id": 244,
        "start": "579240",
        "end": "581300",
        "speakers": "\"00\"",
        "text": "querendo barrar a primeira mulher regente,"
    },
    {
        "id": 245,
        "start": "581520",
        "end": "583220",
        "speakers": "\"00\"",
        "text": "não vai ter golpe nessa cidade."
    },
    {
        "id": 246,
        "start": "583440",
        "end": "585600",
        "speakers": "\"00\"",
        "text": "Tô sendo pra ter algum especial com o próprio"
    },
    {
        "id": 247,
        "start": "585600",
        "end": "587620",
        "speakers": "\"00\"",
        "text": "Anarati. Fico curioso em saber"
    },
    {
        "id": 248,
        "start": "587620",
        "end": "589700",
        "speakers": "\"00\"",
        "text": "a história dele. PS, me sinto"
    },
    {
        "id": 249,
        "start": "589700",
        "end": "591420",
        "speakers": "\"00\"",
        "text": "do mesmo jeito como quando li"
    },
    {
        "id": 250,
        "start": "591420",
        "end": "593980",
        "speakers": "\"00\"",
        "text": "algumas prequels da Crônicas de Gelo e Fogo."
    },
    {
        "id": 251,
        "start": "594320",
        "end": "595560",
        "speakers": "\"00\"",
        "text": "O Anil criança me lembra"
    },
    {
        "id": 252,
        "start": "595560",
        "end": "597560",
        "speakers": "\"00\"",
        "text": "o velho Walder Frey. Criança."
    },
    {
        "id": 253,
        "start": "597980",
        "end": "599280",
        "speakers": "\"00\"",
        "text": "Aprontando o casamento da irmã."
    },
    {
        "id": 254,
        "start": "599420",
        "end": "601600",
        "speakers": "\"00\"",
        "text": "Os cavaleiros também lembram bastante a guarda"
    },
    {
        "id": 255,
        "start": "601600",
        "end": "603940",
        "speakers": "\"00\"",
        "text": "arco-íris e a guarda real."
    },
    {
        "id": 256,
        "start": "604180",
        "end": "605700",
        "speakers": "\"00\"",
        "text": "Muito obrigado pelo seu carinho."
    },
    {
        "id": 257,
        "start": "606100",
        "end": "607400",
        "speakers": "\"00\"",
        "text": "O Anarati é uma"
    },
    {
        "id": 258,
        "start": "607400",
        "end": "609540",
        "speakers": "\"00\"",
        "text": "figura central que a gente pode visitar"
    },
    {
        "id": 259,
        "start": "609540",
        "end": "611760",
        "speakers": "\"00\"",
        "text": "um dia. Acho que isso teria uma história muito bacana"
    },
    {
        "id": 260,
        "start": "611760",
        "end": "613640",
        "speakers": "\"00\"",
        "text": "pra contar dele. Eu só preciso"
    },
    {
        "id": 261,
        "start": "613640",
        "end": "615400",
        "speakers": "\"00\"",
        "text": "de uma boa ideia pra tocar."
    },
    {
        "id": 262,
        "start": "615400",
        "end": "617520",
        "speakers": "\"00\"",
        "text": "Esse episódio foi início de ano."
    },
    {
        "id": 263,
        "start": "617740",
        "end": "619300",
        "speakers": "\"00\"",
        "text": "Não foi aquele episódio de explodir"
    },
    {
        "id": 264,
        "start": "619300",
        "end": "621180",
        "speakers": "\"00\"",
        "text": "cabeça, então teve poucos comentários."
    },
    {
        "id": 265,
        "start": "621540",
        "end": "623480",
        "speakers": "\"00\"",
        "text": "Mas quero agradecer a todo mundo que comentou aqui."
    },
    {
        "id": 266,
        "start": "623860",
        "end": "625360",
        "speakers": "\"00\"",
        "text": "Quero lembrar vocês que esse"
    },
    {
        "id": 267,
        "start": "625360",
        "end": "627400",
        "speakers": "\"00\"",
        "text": "podcast só existe porque temos padrinhos"
    },
    {
        "id": 268,
        "start": "627580",
        "end": "629680",
        "speakers": "\"00\"",
        "text": "ajudando a pagar a edição. Patronato"
    },
    {
        "id": 269,
        "start": "629680",
        "end": "631860",
        "speakers": "\"00\"",
        "text": "dá direito a um monte de coisa, como a gente sempre fala."
    },
    {
        "id": 270,
        "start": "632160",
        "end": "633940",
        "speakers": "\"00\"",
        "text": "Como gravar vozes, gravar"
    },
    {
        "id": 271,
        "start": "633940",
        "end": "635720",
        "speakers": "\"00\"",
        "text": "as regras, fazer"
    },
    {
        "id": 272,
        "start": "635720",
        "end": "637680",
        "speakers": "\"00\"",
        "text": "parte do grupo do Telegram. Mas eu tô"
    },
    {
        "id": 273,
        "start": "637680",
        "end": "639880",
        "speakers": "\"00\"",
        "text": "aqui hoje pra agradecer"
    },
    {
        "id": 274,
        "start": "639880",
        "end": "641640",
        "speakers": "\"00\"",
        "text": "os novos padrinhos. Então eu quero"
    },
    {
        "id": 275,
        "start": "641640",
        "end": "643480",
        "speakers": "\"00\"",
        "text": "agradecer ao Victor Teruia,"
    },
    {
        "id": 276,
        "start": "643480",
        "end": "645560",
        "speakers": "\"00\"",
        "text": "ao Leonardo Sander Stucker,"
    },
    {
        "id": 277,
        "start": "646040",
        "end": "647480",
        "speakers": "\"00\"",
        "text": "ao Silvio Mizono Rodrigues,"
    },
    {
        "id": 278,
        "start": "648380",
        "end": "649160",
        "speakers": "\"00\"",
        "text": "ao Felipe Mota,"
    },
    {
        "id": 279,
        "start": "649740",
        "end": "651200",
        "speakers": "\"00\"",
        "text": "a Fernanda Alves de Carvalho,"
    },
    {
        "id": 280,
        "start": "651620",
        "end": "653360",
        "speakers": "\"00\"",
        "text": "ao Marcos Assunção, ao Paulo"
    },
    {
        "id": 281,
        "start": "653360",
        "end": "655780",
        "speakers": "\"00\"",
        "text": "Colares, a Joana Albuquerque,"
    },
    {
        "id": 282,
        "start": "656280",
        "end": "657480",
        "speakers": "\"00\"",
        "text": "ao Marcos Henrique Santos,"
    },
    {
        "id": 283,
        "start": "657580",
        "end": "659940",
        "speakers": "\"00\"",
        "text": "ao Santos Ferreira, ao Gabriel Alexandre,"
    },
    {
        "id": 284,
        "start": "660220",
        "end": "661700",
        "speakers": "\"00\"",
        "text": "a Alana Sabihon, é, de novo,"
    },
    {
        "id": 285,
        "start": "661800",
        "end": "662900",
        "speakers": "\"00\"",
        "text": "ela deu problema e me assinou de novo."
    },
    {
        "id": 286,
        "start": "663120",
        "end": "665480",
        "speakers": "\"00\"",
        "text": "João Paulo Buncho, também,"
    },
    {
        "id": 287,
        "start": "665840",
        "end": "667240",
        "speakers": "\"00\"",
        "text": "né, em casal, olha só."
    },
    {
        "id": 288,
        "start": "667800",
        "end": "668960",
        "speakers": "\"00\"",
        "text": "Denis Carvalho,"
    },
    {
        "id": 289,
        "start": "669380",
        "end": "671160",
        "speakers": "\"00\"",
        "text": "o Josair Gonçalves Júnior,"
    },
    {
        "id": 290,
        "start": "671520",
        "end": "673180",
        "speakers": "\"00\"",
        "text": "o Vitor Prá Medeiros,"
    },
    {
        "id": 291,
        "start": "673500",
        "end": "675400",
        "speakers": "\"00\"",
        "text": "Carlos Vitor, Alexandre"
    },
    {
        "id": 292,
        "start": "675400",
        "end": "677540",
        "speakers": "\"00\"",
        "text": "Ascioli, Maurício Jussum,"
    },
    {
        "id": 293,
        "start": "677900",
        "end": "679760",
        "speakers": "\"00\"",
        "text": "Evandro Hoffman, Marcos"
    },
    {
        "id": 294,
        "start": "679760",
        "end": "681420",
        "speakers": "\"00\"",
        "text": "Matias, ao Alfa,"
    },
    {
        "id": 295,
        "start": "681760",
        "end": "683100",
        "speakers": "\"00\"",
        "text": "ao Lucas Costa Braga"
    },
    {
        "id": 296,
        "start": "683100",
        "end": "685200",
        "speakers": "\"00\"",
        "text": "e ao Matheus Belo."
    },
    {
        "id": 297,
        "start": "685200",
        "end": "687340",
        "speakers": "\"00\"",
        "text": "Muito obrigado a todos vocês"
    },
    {
        "id": 298,
        "start": "687340",
        "end": "689500",
        "speakers": "\"00\"",
        "text": "que apoiaram esse projeto, muito obrigado"
    },
    {
        "id": 299,
        "start": "689500",
        "end": "691120",
        "speakers": "\"00\"",
        "text": "e isso faz com que saiam"
    },
    {
        "id": 300,
        "start": "691120",
        "end": "692740",
        "speakers": "\"00\"",
        "text": "cada vez mais episódios."
    },
    {
        "id": 301,
        "start": "693120",
        "end": "695280",
        "speakers": "\"00\"",
        "text": "Um beijo no coração de vocês e semana que"
    },
    {
        "id": 302,
        "start": "695280",
        "end": "697040",
        "speakers": "\"00\"",
        "text": "vem teremos um casamento"
    },
    {
        "id": 303,
        "start": "697040",
        "end": "697780",
        "speakers": "\"00\"",
        "text": "no seu feed."
    },
    {
        "id": 304,
        "start": "713300",
        "end": "715400",
        "speakers": "\"00\"",
        "text": "Eu sei que você tá aqui esperando uma cena extra,"
    },
    {
        "id": 305,
        "start": "715540",
        "end": "717260",
        "speakers": "\"00\"",
        "text": "mas eu tô de férias e como muitas"
    },
    {
        "id": 306,
        "start": "717260",
        "end": "719300",
        "speakers": "\"00\"",
        "text": "vezes a gente comentou, é um episódio mais simples."
    },
    {
        "id": 307,
        "start": "719640",
        "end": "721180",
        "speakers": "\"00\"",
        "text": "Então eu vou deixar aqui uma coisa"
    },
    {
        "id": 308,
        "start": "721180",
        "end": "723140",
        "speakers": "\"00\"",
        "text": "que o Pedro Love fez e que eu achei"
    },
    {
        "id": 309,
        "start": "723140",
        "end": "724640",
        "speakers": "\"00\"",
        "text": "maravilhosa. Aumenta o som."
    },
    {
        "id": 310,
        "start": "725720",
        "end": "727260",
        "speakers": "\"01\"",
        "text": "O Realidades Paralelas"
    },
    {
        "id": 311,
        "start": "727800",
        "end": "729280",
        "speakers": "\"01\"",
        "text": "do Guaxinim"
    },
    {
        "id": 312,
        "start": "729280",
        "end": "731320",
        "speakers": "\"01\"",
        "text": "Usa o sistema"
    },
    {
        "id": 313,
        "start": "731320",
        "end": "733260",
        "speakers": "\"01, 00\"",
        "text": "guaxinim e gambiás"
    },
    {
        "id": 314,
        "start": "734300",
        "end": "737460",
        "speakers": "\"01\"",
        "text": "Nele cada jogador"
    },
    {
        "id": 315,
        "start": "737460",
        "end": "739380",
        "speakers": "\"01\"",
        "text": "possui apenas"
    },
    {
        "id": 316,
        "start": "739380",
        "end": "741400",
        "speakers": "\"01\"",
        "text": "um único atributo"
    },
    {
        "id": 317,
        "start": "741400",
        "end": "743720",
        "speakers": "\"01, 00\"",
        "text": "que vai de 2 a 5"
    },
    {
        "id": 318,
        "start": "745260",
        "end": "747220",
        "speakers": "\"01\"",
        "text": "Quanto maior"
    },
    {
        "id": 319,
        "start": "747220",
        "end": "748680",
        "speakers": "\"01\"",
        "text": "o atributo"
    },
    {
        "id": 320,
        "start": "748680",
        "end": "751220",
        "speakers": "\"01\"",
        "text": "mais atlético é o"
    },
    {
        "id": 321,
        "start": "751220",
        "end": "752560",
        "speakers": "\"01\"",
        "text": "personagem"
    },
    {
        "id": 322,
        "start": "752560",
        "end": "754560",
        "speakers": "\"01\"",
        "text": "Quanto menor"
    },
    {
        "id": 323,
        "start": "754560",
        "end": "757180",
        "speakers": "\"01\"",
        "text": "mais inteligente"
    },
    {
        "id": 324,
        "start": "757180",
        "end": "758300",
        "speakers": "\"01\"",
        "text": "e carismático"
    },
    {
        "id": 325,
        "start": "758300",
        "end": "761180",
        "speakers": "\"01\"",
        "text": "Sempre"
    },
    {
        "id": 326,
        "start": "761180",
        "end": "763120",
        "speakers": "\"01\"",
        "text": "que o jogador faz"
    },
    {
        "id": 327,
        "start": "763120",
        "end": "765400",
        "speakers": "\"01\"",
        "text": "algo com uma chance"
    },
    {
        "id": 328,
        "start": "765400",
        "end": "766840",
        "speakers": "\"01\"",
        "text": "de errar"
    },
    {
        "id": 329,
        "start": "766840",
        "end": "768540",
        "speakers": "\"01\"",
        "text": "Joga dois dados"
    },
    {
        "id": 330,
        "start": "768540",
        "end": "771340",
        "speakers": "\"01\"",
        "text": "e precisa tirar seu atributo"
    },
    {
        "id": 331,
        "start": "771340",
        "end": "772120",
        "speakers": "\"01\"",
        "text": "ou menos"
    },
    {
        "id": 332,
        "start": "772120",
        "end": "775380",
        "speakers": "\"01\"",
        "text": "Pra ataques e ações físicas"
    },
    {
        "id": 333,
        "start": "775380",
        "end": "776680",
        "speakers": "\"01\"",
        "text": "Seu atributo"
    },
    {
        "id": 334,
        "start": "776680",
        "end": "776760",
        "speakers": "\"01\"",
        "text": "Seu atributo"
    },
    {
        "id": 335,
        "start": "776760",
        "end": "777200",
        "speakers": "\"01\"",
        "text": "Seu atributo"
    },
    {
        "id": 336,
        "start": "777200",
        "end": "778700",
        "speakers": "\"01\"",
        "text": "ou mais"
    },
    {
        "id": 337,
        "start": "778700",
        "end": "781020",
        "speakers": "\"01\"",
        "text": "Pra ações intelectuais"
    },
    {
        "id": 338,
        "start": "781020",
        "end": "782260",
        "speakers": "\"01\"",
        "text": "ou sociais"
    },
    {
        "id": 339,
        "start": "782260",
        "end": "785540",
        "speakers": "\"01\"",
        "text": "E se a jogada for fácil"
    },
    {
        "id": 340,
        "start": "785540",
        "end": "788380",
        "speakers": "\"01\"",
        "text": "Ou tiver algum auxílio"
    },
    {
        "id": 341,
        "start": "788380",
        "end": "790700",
        "speakers": "\"01\"",
        "text": "Joga um dado a mais"
    },
    {
        "id": 342,
        "start": "790700",
        "end": "793200",
        "speakers": "\"01\"",
        "text": "Se a jogada for difícil"
    },
    {
        "id": 343,
        "start": "793780",
        "end": "796580",
        "speakers": "\"01\"",
        "text": "Rola-se um dado"
    },
    {
        "id": 344,
        "start": "796580",
        "end": "797380",
        "speakers": "\"01\"",
        "text": "a menos"
    },
    {
        "id": 345,
        "start": "797380",
        "end": "799380",
        "speakers": "\"01\"",
        "text": "Eu sou"
    },
    {
        "id": 346,
        "start": "799380",
        "end": "800500",
        "speakers": "\"01\"",
        "text": "Pedro Love"
    },
    {
        "id": 347,
        "start": "800500",
        "end": "803420",
        "speakers": "\"01\"",
        "text": "Eu sou padrinho"
    },
    {
        "id": 348,
        "start": "803420",
        "end": "805120",
        "speakers": "\"01\"",
        "text": "do RP Guaxa"
    },
    {
        "id": 349,
        "start": "805120",
        "end": "807120",
        "speakers": "\"01\"",
        "text": "Porque essas histórias"
    },
    {
        "id": 350,
        "start": "807200",
        "end": "809320",
        "speakers": "\"01\"",
        "text": "incríveis"
    },
    {
        "id": 351,
        "start": "809320",
        "end": "812320",
        "speakers": "\"01\"",
        "text": "Me fizeram expandir"
    },
    {
        "id": 352,
        "start": "812320",
        "end": "814320",
        "speakers": "\"01\"",
        "text": "O que eu conhecia"
    },
    {
        "id": 353,
        "start": "814320",
        "end": "817320",
        "speakers": "\"01\"",
        "text": "por RPG"
    }
]